Compiled from "ElementTypeConverters.kt"
public final class com.intellij.platform.syntax.psi.ElementTypeConverters {
  public static final com.intellij.platform.syntax.psi.ElementTypeConverters INSTANCE;

  private static final java.util.concurrent.ConcurrentHashMap<com.intellij.lang.Language, com.intellij.platform.syntax.psi.ElementTypeConverter> cache;

  private static final com.intellij.lang.LanguageExtension<com.intellij.platform.syntax.psi.ElementTypeConverterFactory> instance;

  private com.intellij.platform.syntax.psi.ElementTypeConverters();
    Code:
       0: aload_0
       1: invokespecial #8                  // Method java/lang/Object."<init>":()V
       4: return

  public static final com.intellij.lang.LanguageExtension<com.intellij.platform.syntax.psi.ElementTypeConverterFactory> getInstance();
    Code:
       0: getstatic     #18                 // Field instance:Lcom/intellij/lang/LanguageExtension;
       3: areturn

  public static void getInstance$annotations();
    Code:
       0: return

  public static final com.intellij.platform.syntax.psi.ElementTypeConverter getConverter(com.intellij.lang.Language);
    Code:
       0: getstatic     #26                 // Field cache:Ljava/util/concurrent/ConcurrentHashMap;
       3: checkcast     #28                 // class java/util/concurrent/ConcurrentMap
       6: astore_1
       7: aload_0
       8: astore_2
       9: iconst_0
      10: istore_3
      11: aload_1
      12: aload_2
      13: invokeinterface #32,  2           // InterfaceMethod java/util/concurrent/ConcurrentMap.get:(Ljava/lang/Object;)Ljava/lang/Object;
      18: dup
      19: ifnonnull     113
      22: pop
      23: iconst_0
      24: istore        4
      26: getstatic     #35                 // Field INSTANCE:Lcom/intellij/platform/syntax/psi/ElementTypeConverters;
      29: aload_0
      30: invokespecial #38                 // Method inferConverter:(Lcom/intellij/lang/Language;)Lcom/intellij/platform/syntax/psi/ElementTypeConverter;
      33: dup
      34: ifnonnull     90
      37: pop
      38: getstatic     #35                 // Field INSTANCE:Lcom/intellij/platform/syntax/psi/ElementTypeConverters;
      41: astore        5
      43: iconst_0
      44: istore        6
      46: iconst_0
      47: istore        7
      49: ldc           #2                  // class com/intellij/platform/syntax/psi/ElementTypeConverters
      51: invokestatic  #43                 // Method com/intellij/openapi/diagnostic/Logger.getInstance:(Ljava/lang/Class;)Lcom/intellij/openapi/diagnostic/Logger;
      54: dup
      55: ldc           #45                 // String getInstance(...)
      57: invokestatic  #51                 // Method kotlin/jvm/internal/Intrinsics.checkNotNullExpressionValue:(Ljava/lang/Object;Ljava/lang/String;)V
      60: new           #53                 // class java/lang/StringBuilder
      63: dup
      64: invokespecial #54                 // Method java/lang/StringBuilder."<init>":()V
      67: ldc           #56                 // String No ElementTypeConverter for language
      69: invokevirtual #60                 // Method java/lang/StringBuilder.append:(Ljava/lang/String;)Ljava/lang/StringBuilder;
      72: aload_0
      73: invokevirtual #63                 // Method java/lang/StringBuilder.append:(Ljava/lang/Object;)Ljava/lang/StringBuilder;
      76: invokevirtual #67                 // Method java/lang/StringBuilder.toString:()Ljava/lang/String;
      79: invokevirtual #71                 // Method com/intellij/openapi/diagnostic/Logger.error:(Ljava/lang/String;)V
      82: iconst_0
      83: anewarray     #73                 // class kotlin/Pair
      86: invokestatic  #79                 // Method com/intellij/platform/syntax/psi/ElementTypeConverterKt.elementTypeConverterOf:([Lkotlin/Pair;)Lcom/intellij/platform/syntax/psi/ElementTypeConverter;
      89: nop
      90: nop
      91: astore        8
      93: iconst_0
      94: istore        9
      96: aload_1
      97: aload_2
      98: aload         8
     100: invokeinterface #83,  3           // InterfaceMethod java/util/concurrent/ConcurrentMap.putIfAbsent:(Ljava/lang/Object;Ljava/lang/Object;)Ljava/lang/Object;
     105: dup
     106: ifnonnull     112
     109: pop
     110: aload         8
     112: nop
     113: nop
     114: checkcast     #85                 // class com/intellij/platform/syntax/psi/ElementTypeConverter
     117: areturn

  private final com.intellij.platform.syntax.psi.ElementTypeConverter inferConverter(com.intellij.lang.Language);
    Code:
       0: getstatic     #18                 // Field instance:Lcom/intellij/lang/LanguageExtension;
       3: aload_1
       4: invokevirtual #107                // Method com/intellij/lang/LanguageExtension.allForLanguage:(Lcom/intellij/lang/Language;)Ljava/util/List;
       7: astore_2
       8: aload_2
       9: invokeinterface #113,  1          // InterfaceMethod java/util/List.isEmpty:()Z
      14: ifeq          19
      17: aconst_null
      18: areturn
      19: aload_2
      20: invokeinterface #117,  1          // InterfaceMethod java/util/List.size:()I
      25: iconst_1
      26: if_icmpne     42
      29: aload_2
      30: invokestatic  #123                // Method kotlin/collections/CollectionsKt.single:(Ljava/util/List;)Ljava/lang/Object;
      33: checkcast     #125                // class com/intellij/platform/syntax/psi/ElementTypeConverterFactory
      36: invokeinterface #129,  1          // InterfaceMethod com/intellij/platform/syntax/psi/ElementTypeConverterFactory.getElementTypeConverter:()Lcom/intellij/platform/syntax/psi/ElementTypeConverter;
      41: areturn
      42: aload_2
      43: checkcast     #131                // class java/lang/Iterable
      46: astore_3
      47: iconst_0
      48: istore        4
      50: aload_3
      51: astore        5
      53: new           #133                // class java/util/ArrayList
      56: dup
      57: aload_3
      58: bipush        10
      60: invokestatic  #137                // Method kotlin/collections/CollectionsKt.collectionSizeOrDefault:(Ljava/lang/Iterable;I)I
      63: invokespecial #140                // Method java/util/ArrayList."<init>":(I)V
      66: checkcast     #142                // class java/util/Collection
      69: astore        6
      71: iconst_0
      72: istore        7
      74: aload         5
      76: invokeinterface #146,  1          // InterfaceMethod java/lang/Iterable.iterator:()Ljava/util/Iterator;
      81: astore        8
      83: aload         8
      85: invokeinterface #151,  1          // InterfaceMethod java/util/Iterator.hasNext:()Z
      90: ifeq          135
      93: aload         8
      95: invokeinterface #155,  1          // InterfaceMethod java/util/Iterator.next:()Ljava/lang/Object;
     100: astore        9
     102: aload         6
     104: aload         9
     106: checkcast     #125                // class com/intellij/platform/syntax/psi/ElementTypeConverterFactory
     109: astore        10
     111: astore        12
     113: iconst_0
     114: istore        11
     116: aload         10
     118: invokeinterface #129,  1          // InterfaceMethod com/intellij/platform/syntax/psi/ElementTypeConverterFactory.getElementTypeConverter:()Lcom/intellij/platform/syntax/psi/ElementTypeConverter;
     123: aload         12
     125: swap
     126: invokeinterface #159,  2          // InterfaceMethod java/util/Collection.add:(Ljava/lang/Object;)Z
     131: pop
     132: goto          83
     135: aload         6
     137: checkcast     #109                // class java/util/List
     140: nop
     141: invokestatic  #163                // Method com/intellij/platform/syntax/psi/ElementTypeConverterKt.compositeElementTypeConverter:(Ljava/util/List;)Lcom/intellij/platform/syntax/psi/ElementTypeConverter;
     144: areturn

  public static final java.util.concurrent.ConcurrentHashMap access$getCache$p();
    Code:
       0: getstatic     #26                 // Field cache:Ljava/util/concurrent/ConcurrentHashMap;
       3: areturn

  static {};
    Code:
       0: new           #2                  // class com/intellij/platform/syntax/psi/ElementTypeConverters
       3: dup
       4: invokespecial #180                // Method "<init>":()V
       7: putstatic     #35                 // Field INSTANCE:Lcom/intellij/platform/syntax/psi/ElementTypeConverters;
      10: new           #182                // class java/util/concurrent/ConcurrentHashMap
      13: dup
      14: invokespecial #183                // Method java/util/concurrent/ConcurrentHashMap."<init>":()V
      17: putstatic     #26                 // Field cache:Ljava/util/concurrent/ConcurrentHashMap;
      20: new           #185                // class com/intellij/platform/syntax/psi/ElementTypeConverters$instance$1
      23: dup
      24: invokespecial #186                // Method com/intellij/platform/syntax/psi/ElementTypeConverters$instance$1."<init>":()V
      27: checkcast     #103                // class com/intellij/lang/LanguageExtension
      30: putstatic     #18                 // Field instance:Lcom/intellij/lang/LanguageExtension;
      33: return
}
